LICENSE.txt
README.md
setup.cfg
setup.py
TOPSIS_TUSHAR_102003137/__init__.py
TOPSIS_TUSHAR_102003137/topsis_102003137.py
TOPSIS_TUSHAR_102003137.egg-info/PKG-INFO
TOPSIS_TUSHAR_102003137.egg-info/SOURCES.txt
TOPSIS_TUSHAR_102003137.egg-info/dependency_links.txt
TOPSIS_TUSHAR_102003137.egg-info/requires.txt
TOPSIS_TUSHAR_102003137.egg-info/top_level.txt